{"global_history":["A4","A3","A2","A1"],"spreadsheet":{"A1":{"cell_history":[{"contents":"Peter Forsling","dependents":[],"name":"A1","type":"string"}],"contents":"Peter Forsling","dependents":[],"type":"string","undo_history":[{"contents":"Peter Forsling","dependents":[],"name":"A1","type":"string"}]},"A2":{"cell_history":[{"contents":"=2 + 2","dependents":[],"name":"A2","type":"string"}],"contents":"=2 + 2","dependents":[],"type":"string","undo_history":[{"contents":"=2 + 2","dependents":[],"name":"A2","type":"string"}]},"A3":{"cell_history":[{"contents":"=A2 - 1","dependents":["A2"],"name":"A3","type":"string"}],"contents":"=A2 - 1","dependents":["A2"],"type":"string","undo_history":[{"contents":"=A2 - 1","dependents":["A2"],"name":"A3","type":"string"}]},"A4":{"cell_history":[{"contents":"12.300000","dependents":[],"name":"A4","type":"double"}],"contents":"12.300000","dependents":[],"type":"double","undo_history":[{"contents":"12.300000","dependents":[],"name":"A4","type":"double"}]}}}{"global_history":["C3","C2","C1","A4","A3","A2","A1"],"spreadsheet":{"A1":{"cell_history":[{"contents":"Peter Forsling","dependents":[],"name":"A1","type":"string"}],"contents":"Peter Forsling","dependents":[],"type":"string","undo_history":[{"contents":"Peter Forsling","dependents":[],"name":"A1","type":"string"}]},"A2":{"cell_history":[{"contents":"=2 + 2","dependents":[],"name":"A2","type":"string"}],"contents":"=2 + 2","dependents":[],"type":"string","undo_history":[{"contents":"=2 + 2","dependents":[],"name":"A2","type":"string"}]},"A3":{"cell_history":[{"contents":"=A2 - 1","dependents":["A2"],"name":"A3","type":"string"}],"contents":"=A2 - 1","dependents":["A2"],"type":"string","undo_history":[{"contents":"=A2 - 1","dependents":["A2"],"name":"A3","type":"string"}]},"A4":{"cell_history":[{"contents":"12.300000","dependents":[],"name":"A4","type":"double"}],"contents":"12.300000","dependents":[],"type":"double","undo_history":[{"contents":"12.300000","dependents":[],"name":"A4","type":"double"}]},"C1":{"cell_history":[{"contents":"Richard Timpson","dependents":[],"name":"C1","type":"string"}],"contents":"Richard Timpson","dependents":[],"type":"string","undo_history":[{"contents":"Richard Timpson","dependents":[],"name":"C1","type":"string"}]},"C2":{"cell_history":[{"contents":"is","dependents":[],"name":"C2","type":"string"}],"contents":"is","dependents":[],"type":"string","undo_history":[{"contents":"is","dependents":[],"name":"C2","type":"string"}]},"C3":{"cell_history":[{"contents":"qt","dependents":[],"name":"C3","type":"string"}],"contents":"qt","dependents":[],"type":"string","undo_history":[{"contents":"qt","dependents":[],"name":"C3","type":"string"}]}}}{"global_history":["A4","A3","A2","A1"],"spreadsheet":{"A1":{"cell_history":[{"contents":"Peter Forsling","dependents":[],"name":"A1","type":"string"}],"contents":"Peter Forsling","dependents":[],"type":"string","undo_history":[{"contents":"Peter Forsling","dependents":[],"name":"A1","type":"string"}]},"A2":{"cell_history":[{"contents":"=2 + 2","dependents":[],"name":"A2","type":"string"}],"contents":"=2 + 2","dependents":[],"type":"string","undo_history":[{"contents":"=2 + 2","dependents":[],"name":"A2","type":"string"}]},"A3":{"cell_history":[{"contents":"=A2 - 1","dependents":["A2"],"name":"A3","type":"string"}],"contents":"=A2 - 1","dependents":["A2"],"type":"string","undo_history":[{"contents":"=A2 - 1","dependents":["A2"],"name":"A3","type":"string"}]},"A4":{"cell_history":[{"contents":"12.300000","dependents":[],"name":"A4","type":"double"}],"contents":"12.300000","dependents":[],"type":"double","undo_history":[{"contents":"12.300000","dependents":[],"name":"A4","type":"double"}]}}}